MANIFEST.in
README.md
setup.py
ace/.directory
ace/Erros.txt
ace/LICENSE
ace/README.md
ace/__init__.py
ace/admin.py
ace/apps.py
ace/autocompleteviews.py
ace/changelog.rst
ace/changelog.txt
ace/fabfile.py
ace/filters.py
ace/forms.py
ace/models.py
ace/reports.py
ace/requirements.txt
ace/snmp.py
ace/tables.py
ace/tests.py
ace/todo.txt
ace/urls.py
ace/version.txt
ace/views.py
ace/docs/Makefile
ace/docs/make.bat
ace/docs/build/.buildinfo
ace/docs/build/.directory
ace/docs/build/bens.html
ace/docs/build/changelog.html
ace/docs/build/contato.html
ace/docs/build/equipamentos.html
ace/docs/build/genindex.html
ace/docs/build/help.html
ace/docs/build/index.html
ace/docs/build/install.html
ace/docs/build/licence.html
ace/docs/build/locais.html
ace/docs/build/objects.inv
ace/docs/build/painel.html
ace/docs/build/rede.html
ace/docs/build/search.html
ace/docs/build/searchindex.js
ace/docs/build/telefonia.html
ace/docs/build/usuarios.html
ace/docs/build/.doctrees/bens.doctree
ace/docs/build/.doctrees/changelog.doctree
ace/docs/build/.doctrees/contato.doctree
ace/docs/build/.doctrees/environment (Cópia em conflito de mpf89495 2018-05-17).pickle
ace/docs/build/.doctrees/environment.pickle
ace/docs/build/.doctrees/equipamentos (Cópia em conflito de mpf89495 2018-05-17).doctree
ace/docs/build/.doctrees/equipamentos.doctree
ace/docs/build/.doctrees/help.doctree
ace/docs/build/.doctrees/index (Cópia em conflito de mpf89495 2018-05-17).doctree
ace/docs/build/.doctrees/index.doctree
ace/docs/build/.doctrees/install (Cópia em conflito de mpf89495 2018-05-17).doctree
ace/docs/build/.doctrees/install.doctree
ace/docs/build/.doctrees/licence.doctree
ace/docs/build/.doctrees/locais (Cópia em conflito de mpf89495 2018-05-17).doctree
ace/docs/build/.doctrees/locais.doctree
ace/docs/build/.doctrees/painel.doctree
ace/docs/build/.doctrees/rede.doctree
ace/docs/build/.doctrees/telefonia.doctree
ace/docs/build/.doctrees/usuarios (Cópia em conflito de mpf89495 2018-05-17).doctree
django_sysace.egg-info/PKG-INFO
django_sysace.egg-info/SOURCES.txt
django_sysace.egg-info/dependency_links.txt
django_sysace.egg-info/requires.txt
django_sysace.egg-info/top_level.txt
