Metadata-Version: 1.1
Name: django-sysace
Version: 1.2.8
Summary: ACE is a Django app to administrate networks hosts, ip address, services, racks, patchpanels, phones and more. The system objective is turn the IT Infraestructure adminsitration easyer.
Home-page: https://www.rogeriodacosta.com.br/
Author: Rogerio da Costa Dantas Luiz
Author-email: rogeriocdluiz@gmail.com
License: BSD License
Platform: UNKNOWN
Classifier: Programming Language :: Python :: 2
Classifier: License :: OSI Approved :: MIT License
Classifier: Operating System :: OS Independent
